pymeeus-stubs/Angle.pyi
pymeeus-stubs/Coordinates.pyi
pymeeus-stubs/CurveFitting.pyi
pymeeus-stubs/Earth.pyi
pymeeus-stubs/Epoch.pyi
pymeeus-stubs/Interpolation.pyi
pymeeus-stubs/Jupiter.pyi
pymeeus-stubs/JupiterMoons.pyi
pymeeus-stubs/METADATA.toml
pymeeus-stubs/Mars.pyi
pymeeus-stubs/Mercury.pyi
pymeeus-stubs/Minor.pyi
pymeeus-stubs/Moon.pyi
pymeeus-stubs/Neptune.pyi
pymeeus-stubs/Pluto.pyi
pymeeus-stubs/Saturn.pyi
pymeeus-stubs/Sun.pyi
pymeeus-stubs/Uranus.pyi
pymeeus-stubs/Venus.pyi
pymeeus-stubs/__init__.pyi
pymeeus-stubs/base.pyi
pymeeus-stubs/py.typed
types_pymeeus-0.5.0.20250828.dist-info/licenses/LICENSE
types_pymeeus-0.5.0.20250828.dist-info/METADATA
types_pymeeus-0.5.0.20250828.dist-info/WHEEL
types_pymeeus-0.5.0.20250828.dist-info/top_level.txt
types_pymeeus-0.5.0.20250828.dist-info/RECORD
